manly_randomization_test/__init__.py
manly_randomization_test/manly_randomization_test.py
manly_randomization_test-0.0.1.dist-info/LICENSE
manly_randomization_test-0.0.1.dist-info/METADATA
manly_randomization_test-0.0.1.dist-info/WHEEL
manly_randomization_test-0.0.1.dist-info/top_level.txt
manly_randomization_test-0.0.1.dist-info/RECORD
