Metadata-Version: 2.1
Name: manly-randomization-test
Version: 0.0.1
Summary: A python implementation of Manly randomization test
Author-email: David Stephens <davesteps@gmail.com>
License: Apache License
Project-URL: homepage, https://github.com/davesteps/manly_randomization_test
License-File: LICENSE
Requires-Dist: numpy
Provides-Extra: dev
Requires-Dist: bandit ; extra == 'dev'
Requires-Dist: black ; extra == 'dev'
Requires-Dist: flake8 ; extra == 'dev'
Requires-Dist: isort ; extra == 'dev'
Requires-Dist: mypy ; extra == 'dev'
Requires-Dist: pytest ; extra == 'dev'
Requires-Dist: twine ; extra == 'dev'
